freesopy/__init__.py
freesopy-1.1.0.dist-info/METADATA
freesopy-1.1.0.dist-info/WHEEL
freesopy-1.1.0.dist-info/top_level.txt
freesopy-1.1.0.dist-info/RECORD
