Metadata-Version: 2.1
Name: freesopy
Version: 1.1.0
Summary: This is a Python package for the implementation of various equations of Free Space Optical Communication
Author: Shoaib,Deepak and Tanvi
Requires-Dist: numpy
Requires-Dist: matplotlib
